README.md
setup.py
hwpy/__init__.py
hwpy/__main__.py
hwpy/_dmide.py
hwpy/_hwdisk.py
hwpy/_hwnet.py
hwpy/_hwpart.py
hwpy/info.py
hwpy.egg-info/PKG-INFO
hwpy.egg-info/SOURCES.txt
hwpy.egg-info/dependency_links.txt
hwpy.egg-info/requires.txt
hwpy.egg-info/top_level.txt