Metadata-Version: 2.1
Name: hwpy
Version: 0.2.0
Summary: Show Linux Hardware Info
Home-page: https://github.com/starsliao/hwpy
Author: Stars Liao
Author-email: starsliao@163.com
License: MIT Licence
Keywords: pip,hwpy,Hardware
Platform: any
Classifier: Intended Audience :: System Administrators
Classifier: Operating System :: POSIX :: Linux
Classifier: Programming Language :: Python :: 2.7
Classifier: Programming Language :: Python :: 3
Classifier: Topic :: Utilities
